boletocloud
