Metadata-Version: 1.0
Name: python-boleto-cloud
Version: 0.2
Summary: Integração com a API do boletocloud.com
Home-page: https://github.com/hudsonbrendon/python-boleto-cloud
Author: Hudson Brendon
Author-email: contato.hudsonbrendon@gmail.com
License: MIT
Platform: UNKNOWN
